MANIFEST.in
README.rst
setup.py
collective/__init__.py
collective.singingnotify.egg-info/PKG-INFO
collective.singingnotify.egg-info/SOURCES.txt
collective.singingnotify.egg-info/dependency_links.txt
collective.singingnotify.egg-info/entry_points.txt
collective.singingnotify.egg-info/namespace_packages.txt
collective.singingnotify.egg-info/not-zip-safe
collective.singingnotify.egg-info/requires.txt
collective.singingnotify.egg-info/top_level.txt
collective/singingnotify/__init__.py
collective/singingnotify/configure.zcml
collective/singingnotify/handlers.py
collective/singingnotify/i18n.sh
collective/singingnotify/interfaces.py
collective/singingnotify/mail.py
collective/singingnotify/upgrades.py
collective/singingnotify/upgrades.zcml
collective/singingnotify/locales/collective.singingnotify.pot
collective/singingnotify/locales/it/LC_MESSAGES/collective.singingnotify.mo
collective/singingnotify/locales/it/LC_MESSAGES/collective.singingnotify.po
collective/singingnotify/locales/it/LC_MESSAGES/plone.mo
collective/singingnotify/locales/it/LC_MESSAGES/plone.po
collective/singingnotify/profiles/default/metadata.xml
collective/singingnotify/tests/__init__.py
collective/singingnotify/tests/testing_confirm_notify.py
collective/singingnotify/tests/testing_unsubscribe_notify.py
docs/HISTORY.txt
docs/INSTALL.txt
docs/LICENSE.GPL
docs/LICENSE.txt