Metadata-Version: 1.1
Name: collective.singingnotify
Version: 1.0.1
Summary: A plugin for Singing&Dancing that notify users unsubscriptions
Home-page: http://plone.org/products/collective.singingnotify
Author: RedTurtle Technology
Author-email: sviluppoplone@redturtle.it
License: GPL
Keywords: singing dancing newsletter unsubscribe notification
Platform: UNKNOWN
Classifier: Framework :: Plone
Classifier: Framework :: Plone :: 3.3
Classifier: Framework :: Plone :: 4.0
Classifier: Framework :: Plone :: 4.2
Classifier: Programming Language :: Python
